{
  "timestamp": "2026-03-21T01:54:31.065Z",
  "date": "2026-03-21",
  "time": "01-54-31",
  "store": "coto",
  "totalProducts": 24,
  "lastUpdate": "2026-03-21T01:54:31.065Z",
  "data": [
    {
      "name": "Oferta Coto 1",
      "image": "https://www.coto.com.ar/images/ofertas/AficheMix21.jpg",
      "price": "Ver en tienda",
      "link": "https://www.coto.com.ar/ofertas"
    },
    {
      "name": "Oferta Coto 2",
      "image": "https://www.coto.com.ar/images/ofertas/AficheDescuento21.jpg",
      "price": "Ver en tienda",
      "link": "https://www.coto.com.ar/ofertas"
    },
    {
      "name": "Oferta Coto 3",
      "image": "https://www.coto.com.ar/images/ofertas/AficheCredicoop21.jpg",
      "price": "Ver en tienda",
      "link": "https://www.coto.com.ar/ofertas"
    },
    {
      "name": "Oferta Coto 4",
      "image": "https://www.coto.com.ar/images/ofertas/salonuno190326.jpg",
      "price": "Ver en tienda",
      "link": "https://www.coto.com.ar/ofertas"
    },
    {
      "name": "Oferta Coto 5",
      "image": "https://www.coto.com.ar/images/ofertas/salondos190326.jpg",
      "price": "Ver en tienda",
      "link": "https://www.coto.com.ar/ofertas"
    },
    {
      "name": "Oferta Coto 6",
      "image": "https://www.coto.com.ar/images/ofertas/AficheRenova20.jpg",
      "price": "Ver en tienda",
      "link": "https://www.coto.com.ar/ofertas"
    },
    {
      "name": "Oferta Coto 7",
      "image": "https://www.coto.com.ar/images/ofertas/AficheElectroMotivo1_20.jpg",
      "price": "Ver en tienda",
      "link": "https://www.coto.com.ar/ofertas"
    },
    {
      "name": "Oferta Coto 8",
      "image": "https://www.coto.com.ar/images/ofertas/AficheElectroMotivo2_20.jpg",
      "price": "Ver en tienda",
      "link": "https://www.coto.com.ar/ofertas"
    },
    {
      "name": "Oferta Coto 9",
      "image": "https://www.coto.com.ar/images/ofertas/AficheElectroMotivo3_20.jpg",
      "price": "Ver en tienda",
      "link": "https://www.coto.com.ar/ofertas"
    },
    {
      "name": "Oferta Coto 10",
      "image": "https://www.coto.com.ar/images/ofertas/AficheElectroMotivo4_20.jpg",
      "price": "Ver en tienda",
      "link": "https://www.coto.com.ar/ofertas"
    },
    {
      "name": "Oferta Coto 11",
      "image": "https://www.coto.com.ar/images/ofertas/AficheHogar20.jpg",
      "price": "Ver en tienda",
      "link": "https://www.coto.com.ar/ofertas"
    },
    {
      "name": "Oferta Coto 12",
      "image": "https://www.coto.com.ar/images/catalogos/revistas/semanal-frescos/pages/semanal-frescos-1-160326.jpg",
      "price": "Ver en tienda",
      "link": "https://www.coto.com.ar/ofertas"
    },
    {
      "name": "Oferta Coto 13",
      "image": "https://www.coto.com.ar/images/catalogos/revistas/semanal-alimentos/pages/semanal-alimentos-1-160326.jpg",
      "price": "Ver en tienda",
      "link": "https://www.coto.com.ar/ofertas"
    },
    {
      "name": "Oferta Coto 14",
      "image": "https://www.coto.com.ar/images/catalogos/revistas/semanal-perfumeria/pages/semanal-perfumeria-1-160326.jpg",
      "price": "Ver en tienda",
      "link": "https://www.coto.com.ar/ofertas"
    },
    {
      "name": "Oferta Coto 15",
      "image": "https://www.coto.com.ar/images/catalogos/revistas/semanal-hogar/pages/semanal-hogar-1-160326.jpg",
      "price": "Ver en tienda",
      "link": "https://www.coto.com.ar/ofertas"
    },
    {
      "name": "Oferta Coto 16",
      "image": "https://www.coto.com.ar/images/catalogos/revistas/cuidadooral160326/pages/1.jpg",
      "price": "Ver en tienda",
      "link": "https://www.coto.com.ar/ofertas"
    },
    {
      "name": "Oferta Coto 17",
      "image": "https://www.coto.com.ar/images/ofertas/Afiche-Semana-del-Pescado-1603.jpg",
      "price": "Ver en tienda",
      "link": "https://www.coto.com.ar/ofertas"
    },
    {
      "name": "Oferta Coto 18",
      "image": "https://www.coto.com.ar/images/ofertas/AficheWebBancoCiudad18.jpg",
      "price": "Ver en tienda",
      "link": "https://www.coto.com.ar/ofertas"
    },
    {
      "name": "Oferta Coto 19",
      "image": "https://www.coto.com.ar/images/ofertas/AficheWebBNAElectro-Marzo.jpg",
      "price": "Ver en tienda",
      "link": "https://www.coto.com.ar/ofertas"
    },
    {
      "name": "Oferta Coto 20",
      "image": "https://www.coto.com.ar/images/ofertas/AficheWebBancoCredicoopElectro-MARZO.jpg",
      "price": "Ver en tienda",
      "link": "https://www.coto.com.ar/ofertas"
    },
    {
      "name": "Oferta Coto 21",
      "image": "https://www.coto.com.ar/images/ofertas/AficheWeb-GaliciaCuotas9.jpg",
      "price": "Ver en tienda",
      "link": "https://www.coto.com.ar/ofertas"
    },
    {
      "name": "Oferta Coto 22",
      "image": "https://www.coto.com.ar/images/ofertas/AficheWeb-GaliciaCuotas12.jpg",
      "price": "Ver en tienda",
      "link": "https://www.coto.com.ar/ofertas"
    },
    {
      "name": "Oferta Coto 23",
      "image": "https://www.coto.com.ar/images/ofertas/AficheWebBancoMacroMarzo.jpg",
      "price": "Ver en tienda",
      "link": "https://www.coto.com.ar/ofertas"
    },
    {
      "name": "Oferta Coto 24",
      "image": "https://www.coto.com.ar/images/ofertas/AficheWebBancosRegionales12CuotasMarzo.jpg",
      "price": "Ver en tienda",
      "link": "https://www.coto.com.ar/ofertas"
    }
  ]
}