{
  "timestamp": "2026-02-01T02:12:01.290Z",
  "date": "2026-02-01",
  "time": "02-12-01",
  "store": "coto",
  "totalProducts": 13,
  "lastUpdate": "2026-02-01T02:12:01.290Z",
  "data": [
    {
      "name": "Oferta Coto 1",
      "image": "https://www.coto.com.ar/images/ofertas/AficheDescuento3101.jpg",
      "price": "Ver en tienda",
      "link": "https://www.coto.com.ar/ofertas"
    },
    {
      "name": "Oferta Coto 2",
      "image": "https://www.coto.com.ar/images/ofertas/AficheMix3001.jpg",
      "price": "Ver en tienda",
      "link": "https://www.coto.com.ar/ofertas"
    },
    {
      "name": "Oferta Coto 3",
      "image": "https://www.coto.com.ar/images/ofertas/AficheSalon29_1.jpg",
      "price": "Ver en tienda",
      "link": "https://www.coto.com.ar/ofertas"
    },
    {
      "name": "Oferta Coto 4",
      "image": "https://www.coto.com.ar/images/ofertas/AficheSalon29_2.jpg",
      "price": "Ver en tienda",
      "link": "https://www.coto.com.ar/ofertas"
    },
    {
      "name": "Oferta Coto 5",
      "image": "https://www.coto.com.ar/images/ofertas/AficheElectroMotivo1_3001.jpg",
      "price": "Ver en tienda",
      "link": "https://www.coto.com.ar/ofertas"
    },
    {
      "name": "Oferta Coto 6",
      "image": "https://www.coto.com.ar/images/ofertas/AficheElectroMotivo2_3001.jpg",
      "price": "Ver en tienda",
      "link": "https://www.coto.com.ar/ofertas"
    },
    {
      "name": "Oferta Coto 7",
      "image": "https://www.coto.com.ar/images/ofertas/AficheElectroMotivo3_3001.jpg",
      "price": "Ver en tienda",
      "link": "https://www.coto.com.ar/ofertas"
    },
    {
      "name": "Oferta Coto 8",
      "image": "https://www.coto.com.ar/images/ofertas/AficheHogar3001.jpg",
      "price": "Ver en tienda",
      "link": "https://www.coto.com.ar/ofertas"
    },
    {
      "name": "Oferta Coto 9",
      "image": "https://www.coto.com.ar/images/ofertas/AficheRenova3001.jpg",
      "price": "Ver en tienda",
      "link": "https://www.coto.com.ar/ofertas"
    },
    {
      "name": "Oferta Coto 10",
      "image": "https://www.coto.com.ar/images/catalogos/revistas/perfumeria190126/pages/1.jpg",
      "price": "Ver en tienda",
      "link": "https://www.coto.com.ar/ofertas"
    },
    {
      "name": "Oferta Coto 11",
      "image": "https://www.coto.com.ar/images/catalogos/revistas/semanal260126/pages/1.jpg",
      "price": "Ver en tienda",
      "link": "https://www.coto.com.ar/ofertas"
    },
    {
      "name": "Oferta Coto 12",
      "image": "https://www.coto.com.ar/images/ofertas/AficheWebOfertasHogar2601.jpg",
      "price": "Ver en tienda",
      "link": "https://www.coto.com.ar/ofertas"
    },
    {
      "name": "Oferta Coto 13",
      "image": "https://www.coto.com.ar/images/ofertas/AficheWebOfertasBazar2601.jpg",
      "price": "Ver en tienda",
      "link": "https://www.coto.com.ar/ofertas"
    }
  ]
}